setup.py
PythonCommonTools.egg-info/PKG-INFO
PythonCommonTools.egg-info/SOURCES.txt
PythonCommonTools.egg-info/dependency_links.txt
PythonCommonTools.egg-info/requires.txt
PythonCommonTools.egg-info/top_level.txt
pythoncommontools/__init__.py
pythoncommontools/configurationLoader/__init__.py
pythoncommontools/configurationLoader/configurationLoader.py
pythoncommontools/daemonCommon/__init__.py
pythoncommontools/daemonCommon/daemonCommon.py
pythoncommontools/jsonEncoderDecoder/__init__.py
pythoncommontools/jsonEncoderDecoder/complexJsonEncoderDecoder.py
pythoncommontools/jsonEncoderDecoder/simpleJsonEncoderDecoder.py
pythoncommontools/logger/__init__.py
pythoncommontools/logger/logger.py
pythoncommontools/objectUtil/POPO.py
pythoncommontools/objectUtil/__init__.py
pythoncommontools/objectUtil/objectUtil.py
test/__init__.py
test/commonComplexObjects.py
test/daemonCommon/__init__.py
test/daemonCommon/dummyDaemon.py
test/daemonCommon/testDaemonCommon.py
test/objectUtil/__init__.py
test/objectUtil/testObjectUtil.py