Metadata-Version: 1.1
Name: PythonCommonTools
Version: 0.0.0
Summary: common tools for Python
Home-page: UNKNOWN
Author: UNKNOWN
Author-email: UNKNOWN
License: UNKNOWN
Platform: UNKNOWN
Classifier: Programming Language :: Python :: 3
